wakahiki/__init__.py
wakahiki/__main__.py
wakahiki-0.1.7.dist-info/AUTHORS.rst
wakahiki-0.1.7.dist-info/LICENSE.txt
wakahiki-0.1.7.dist-info/METADATA
wakahiki-0.1.7.dist-info/WHEEL
wakahiki-0.1.7.dist-info/entry_points.txt
wakahiki-0.1.7.dist-info/top_level.txt
wakahiki-0.1.7.dist-info/RECORD
