Metadata-Version: 2.1
Name: wakahiki
Version: 0.1.7
Summary: A multithreaded priority respecting script processor
Home-page: https://github.com/sierra-alpha/wakahiki/
Author: Shaun Alexander
Author-email: shaun@sierraalpha.co.nz
License: gpl3
Project-URL: Documentation, https://github.com/sierra-alpha/wakahiki/
Platform: Linux
Classifier: Development Status :: 2 - Pre-Alpha
Classifier: Topic :: Utilities
Classifier: Topic :: System :: Installation/Setup
Classifier: Programming Language :: Python
Classifier: Programming Language :: Python :: 3
Classifier: Operating System :: POSIX :: Linux
Classifier: Operating System :: Unix
Classifier: Operating System :: MacOS
Classifier: Environment :: Console
Classifier: Intended Audience :: Developers
Classifier: Intended Audience :: System Administrators
Requires-Python: >=3.7
Requires-Dist: click
Requires-Dist: toml
Provides-Extra: testing
Requires-Dist: pytest ; extra == 'testing'
Requires-Dist: pytest-cov ; extra == 'testing'
